casanovogui/__init__.py
casanovogui/configure.py
casanovogui/dialogs.py
casanovogui/evaluate.py
casanovogui/home.py
casanovogui/model.py
casanovogui/run.py
casanovogui/search.py
casanovogui/simple_db.py
casanovogui/spectra.py
casanovogui/utils.py
casanovogui/viewer.py
casanovogui/pages/configure.py
casanovogui/pages/model.py
casanovogui/pages/search.py
casanovogui/pages/spectra.py
casanovogui/pages/viewer.py
casanovogui-0.2.3.dist-info/METADATA
casanovogui-0.2.3.dist-info/WHEEL
casanovogui-0.2.3.dist-info/entry_points.txt
casanovogui-0.2.3.dist-info/top_level.txt
casanovogui-0.2.3.dist-info/RECORD
